bibliographer/__init__.py
bibliographer/cardcatalog.py
bibliographer/enrich.py
bibliographer/py.typed
bibliographer/cli/__init__.py
bibliographer/cli/bibliographer.py
bibliographer/cli/util.py
bibliographer/hugo/__init__.py
bibliographer/ratelimiter/__init__.py
bibliographer/sources/__init__.py
bibliographer/sources/amazon_browser.py
bibliographer/sources/audible.py
bibliographer/sources/covers.py
bibliographer/sources/googlebooks.py
bibliographer/sources/kindle.py
bibliographer/sources/librofm.py
bibliographer/sources/manual.py
bibliographer/sources/openlibrary.py
bibliographer/sources/wikipedia.py
bibliographer/util/__init__.py
bibliographer/util/jsonutil.py
bibliographer-2.0.1.dist-info/licenses/LICENSE
bibliographer-2.0.1.dist-info/METADATA
bibliographer-2.0.1.dist-info/WHEEL
bibliographer-2.0.1.dist-info/entry_points.txt
bibliographer-2.0.1.dist-info/top_level.txt
bibliographer-2.0.1.dist-info/RECORD
