Metadata-Version: 2.4
Name: bibliographer
Version: 2.0.1
Summary: Compile a list of books you've read
Requires-Python: >=3.12
License-File: LICENSE
Requires-Dist: audible
Requires-Dist: requests>=2.32.3
Provides-Extra: dev
Requires-Dist: black>=24.0; extra == "dev"
Requires-Dist: cogapp; extra == "dev"
Requires-Dist: invoke; extra == "dev"
Requires-Dist: mypy>=1.14; extra == "dev"
Requires-Dist: pytest>=8.0; extra == "dev"
Requires-Dist: types-requests>=2.32.0.20241016; extra == "dev"
Dynamic: license-file
